{
    "TC6": {
        "status": "FAILED",
        "timestamp": "2026-06-17T04:37:11.002161",
        "error": "quotes: RetryError[<Future at 0x7026d97b5c70 state=finished raised JSONDecodeError>] | trading: RetryError[<Future at 0x7026d7ba9100 state=finished raised AttributeError>]"
    },
    "MNC": {
        "status": "FAILED",
        "timestamp": "2026-06-17T05:10:16.761112",
        "error": "quotes: RetryError[<Future at 0x79c8d7567e90 state=finished raised JSONDecodeError>] | finance: RetryError[<Future at 0x79c8d7d2b680 state=finished raised ValueError>] | trading: RetryError[<Future at 0x79c8d75b8ec0 state=finished raised AttributeError>]"
    },
    "SIC": {
        "status": "FAILED",
        "timestamp": "2026-06-17T04:37:20.964386",
        "error": "quotes: RetryError[<Future at 0x7026d7fbe3c0 state=finished raised JSONDecodeError>] | finance: RetryError[<Future at 0x7026d7ba9a00 state=finished raised ValueError>] | trading: RetryError[<Future at 0x7026d8b6e1e0 state=finished raised AttributeError>]"
    },
    "PMS": {
        "status": "SUCCESS",
        "timestamp": "2026-06-17T02:14:20.223544",
        "error": null
    },
    "PVC": {
        "status": "SUCCESS",
        "timestamp": "2026-06-17T02:14:20.458260",
        "error": null
    },
    "INN": {
        "status": "SUCCESS",
        "timestamp": "2026-06-17T02:14:20.756085",
        "error": null
    },
    "SDN": {
        "status": "SUCCESS",
        "timestamp": "2026-06-17T02:14:28.442845",
        "error": null
    },
    "RCL": {
        "status": "SUCCESS",
        "timestamp": "2026-06-17T02:14:28.678358",
        "error": null
    },
    "PPP": {
        "status": "SUCCESS",
        "timestamp": "2026-06-17T02:14:29.200122",
        "error": null
    },
    "HKT": {
        "status": "SUCCESS",
        "timestamp": "2026-06-17T02:14:36.811285",
        "error": null
    },
    "SEB": {
        "status": "SUCCESS",
        "timestamp": "2026-06-17T02:14:37.053008",
        "error": null
    },
    "VFS": {
        "status": "SUCCESS",
        "timestamp": "2026-06-17T02:14:37.962999",
        "error": null
    },
    "TTH": {
        "status": "SUCCESS",
        "timestamp": "2026-06-17T02:14:45.645570",
        "error": null
    },
    "PTD": {
        "status": "SUCCESS",
        "timestamp": "2026-06-17T02:14:45.966025",
        "error": null
    },
    "BCF": {
        "status": "SUCCESS",
        "timestamp": "2026-06-17T02:14:46.502311",
        "error": null
    },
    "NDN": {
        "status": "SUCCESS",
        "timestamp": "2026-06-17T02:14:54.378431",
        "error": null
    },
    "DC2": {
        "status": "SUCCESS",
        "timestamp": "2026-06-17T02:14:54.817525",
        "error": null
    },
    "PSD": {
        "status": "SUCCESS",
        "timestamp": "2026-06-17T02:14:55.832060",
        "error": null
    },
    "PCE": {
        "status": "SUCCESS",
        "timestamp": "2026-06-17T04:23:07.509561",
        "error": null
    },
    "ARM": {
        "status": "SUCCESS",
        "timestamp": "2026-06-17T04:23:07.742102",
        "error": null
    },
    "NAP": {
        "status": "SUCCESS",
        "timestamp": "2026-06-17T04:23:07.968331",
        "error": null
    },
    "VE1": {
        "status": "SUCCESS",
        "timestamp": "2026-06-17T04:23:08.155549",
        "error": null
    },
    "CIC": {
        "status": "FAILED",
        "timestamp": "2026-06-17T04:37:12.561018",
        "error": "quotes: RetryError[<Future at 0x7026d7761130 state=finished raised JSONDecodeError>] | trading: RetryError[<Future at 0x7026d7ba8bf0 state=finished raised AttributeError>]"
    },
    "QTC": {
        "status": "SUCCESS",
        "timestamp": "2026-06-17T04:23:55.722953",
        "error": null
    },
    "HLC": {
        "status": "SUCCESS",
        "timestamp": "2026-06-17T04:23:55.924444",
        "error": null
    },
    "SGH": {
        "status": "SUCCESS",
        "timestamp": "2026-06-17T04:26:57.119017",
        "error": null
    },
    "SFN": {
        "status": "SUCCESS",
        "timestamp": "2026-06-17T04:26:58.013881",
        "error": null
    },
    "TIG": {
        "status": "SUCCESS",
        "timestamp": "2026-06-17T04:27:05.181363",
        "error": null
    },
    "TXM": {
        "status": "SUCCESS",
        "timestamp": "2026-06-17T04:30:29.237666",
        "error": null
    },
    "VCS": {
        "status": "SUCCESS",
        "timestamp": "2026-06-17T04:30:29.427738",
        "error": null
    },
    "HOM": {
        "status": "SUCCESS",
        "timestamp": "2026-06-17T04:30:37.589957",
        "error": null
    },
    "SMT": {
        "status": "SUCCESS",
        "timestamp": "2026-06-17T04:30:37.769767",
        "error": null
    },
    "TDT": {
        "status": "SUCCESS",
        "timestamp": "2026-06-17T04:37:29.301781",
        "error": null
    },
    "PTI": {
        "status": "SUCCESS",
        "timestamp": "2026-06-17T04:37:37.486728",
        "error": null
    },
    "BTS": {
        "status": "SUCCESS",
        "timestamp": "2026-06-17T04:47:56.542084",
        "error": null
    },
    "NRC": {
        "status": "SUCCESS",
        "timestamp": "2026-06-17T04:47:56.762249",
        "error": null
    },
    "VNC": {
        "status": "SUCCESS",
        "timestamp": "2026-06-17T04:48:05.050041",
        "error": null
    },
    "THS": {
        "status": "SUCCESS",
        "timestamp": "2026-06-17T04:48:05.344325",
        "error": null
    },
    "PIC": {
        "status": "SUCCESS",
        "timestamp": "2026-06-17T04:48:13.521934",
        "error": null
    },
    "TPP": {
        "status": "SUCCESS",
        "timestamp": "2026-06-17T04:48:22.063019",
        "error": null
    },
    "MDC": {
        "status": "SUCCESS",
        "timestamp": "2026-06-17T04:48:31.100876",
        "error": null
    },
    "S91": {
        "status": "FAILED",
        "timestamp": "2026-06-17T05:10:15.891196",
        "error": "quotes: RetryError[<Future at 0x79c8d9d95700 state=finished raised JSONDecodeError>] | finance: RetryError[<Future at 0x79c8d79fd340 state=finished raised ValueError>] | trading: RetryError[<Future at 0x79c8d75b9df0 state=finished raised AttributeError>]"
    },
    "MED": {
        "status": "SUCCESS",
        "timestamp": "2026-06-17T04:48:39.455590",
        "error": null
    },
    "TVC": {
        "status": "SUCCESS",
        "timestamp": "2026-06-17T04:48:49.144933",
        "error": null
    },
    "FID": {
        "status": "SUCCESS",
        "timestamp": "2026-06-17T04:48:57.744872",
        "error": null
    },
    "PGN": {
        "status": "SUCCESS",
        "timestamp": "2026-06-17T04:49:06.092434",
        "error": null
    },
    "NLC": {
        "status": "FAILED",
        "timestamp": "2026-06-17T05:10:17.202317",
        "error": "quotes: RetryError[<Future at 0x79c8d7d2a660 state=finished raised JSONDecodeError>] | finance: RetryError[<Future at 0x79c8d9d955e0 state=finished raised ValueError>] | trading: RetryError[<Future at 0x79c8d75bbb90 state=finished raised AttributeError>]"
    },
    "GFC": {
        "status": "FAILED",
        "timestamp": "2026-06-17T05:10:17.013528",
        "error": "quotes: RetryError[<Future at 0x79c8d75670b0 state=finished raised JSONDecodeError>] | finance: RetryError[<Future at 0x79c8d6d2c8c0 state=finished raised ValueError>] | trading: RetryError[<Future at 0x79c8d75bac60 state=finished raised AttributeError>]"
    },
    "BXH": {
        "status": "SUCCESS",
        "timestamp": "2026-06-17T05:01:07.775429",
        "error": null
    },
    "VIF": {
        "status": "SUCCESS",
        "timestamp": "2026-06-17T05:01:07.991911",
        "error": null
    },
    "OCH": {
        "status": "SUCCESS",
        "timestamp": "2026-06-17T05:01:08.188659",
        "error": null
    },
    "CIA": {
        "status": "SUCCESS",
        "timestamp": "2026-06-17T05:01:17.144098",
        "error": null
    },
    "PSC": {
        "status": "SUCCESS",
        "timestamp": "2026-06-17T05:01:17.347696",
        "error": null
    },
    "TMC": {
        "status": "SUCCESS",
        "timestamp": "2026-06-17T05:10:26.164210",
        "error": null
    },
    "STP": {
        "status": "SUCCESS",
        "timestamp": "2026-06-17T05:10:26.392338",
        "error": null
    },
    "DST": {
        "status": "SUCCESS",
        "timestamp": "2026-06-17T05:10:35.178024",
        "error": null
    },
    "CMC": {
        "status": "SUCCESS",
        "timestamp": "2026-06-17T05:10:35.434224",
        "error": null
    }
}